kicad_coil_maker/__init__.py
kicad_coil_maker/kicad_draw.py
kicad_coil_maker-0.1.0.dist-info/LICENSE
kicad_coil_maker-0.1.0.dist-info/METADATA
kicad_coil_maker-0.1.0.dist-info/WHEEL
kicad_coil_maker-0.1.0.dist-info/RECORD
