Metadata-Version: 2.1
Name: kicad-coil-maker
Version: 0.1.0
Summary: 
Author: t-sasatani
Author-email: sasatani.dev@gmail.com
Requires-Python: >=3.10,<4.0
Classifier: Programming Language :: Python :: 3
Classifier: Programming Language :: Python :: 3.10
Classifier: Programming Language :: Python :: 3.11
Requires-Dist: numpy (>=1.25.2,<2.0.0)
